asynhttp/__init__.py
asynhttp/_cookie_helpers.py
asynhttp/abc.py
asynhttp/base_protocol.py
asynhttp/client.py
asynhttp/client_exceptions.py
asynhttp/client_middleware_digest_auth.py
asynhttp/client_middlewares.py
asynhttp/client_proto.py
asynhttp/client_reqrep.py
asynhttp/client_ws.py
asynhttp/compression_utils.py
asynhttp/connector.py
asynhttp/cookiejar.py
asynhttp/formdata.py
asynhttp/hdrs.py
asynhttp/helpers.py
asynhttp/http.py
asynhttp/http_exceptions.py
asynhttp/http_parser.py
asynhttp/http_websocket.py
asynhttp/http_writer.py
asynhttp/log.py
asynhttp/multipart.py
asynhttp/payload.py
asynhttp/payload_streamer.py
asynhttp/pytest_plugin.py
asynhttp/resolver.py
asynhttp/streams.py
asynhttp/tcp_helpers.py
asynhttp/test_utils.py
asynhttp/tracing.py
asynhttp/typedefs.py
asynhttp/web.py
asynhttp/web_app.py
asynhttp/web_exceptions.py
asynhttp/web_fileresponse.py
asynhttp/web_log.py
asynhttp/web_middlewares.py
asynhttp/web_protocol.py
asynhttp/web_request.py
asynhttp/web_response.py
asynhttp/web_routedef.py
asynhttp/web_runner.py
asynhttp/web_server.py
asynhttp/web_urldispatcher.py
asynhttp/web_ws.py
asynhttp/worker.py
asynhttp/__pycache__/connection.pyc
asynhttp/_websocket/__init__.py
asynhttp/_websocket/helpers.py
asynhttp/_websocket/models.py
asynhttp/_websocket/reader.py
asynhttp/_websocket/reader_c.py
asynhttp/_websocket/reader_py.py
asynhttp/_websocket/writer.py
asynhttp-3.13.1.dist-info/METADATA
asynhttp-3.13.1.dist-info/WHEEL
asynhttp-3.13.1.dist-info/top_level.txt
asynhttp-3.13.1.dist-info/RECORD
